wrfrun-0.1.9.dist-info/METADATA
wrfrun-0.1.9.dist-info/WHEEL
wrfrun-0.1.9.dist-info/entry_points.txt
wrfrun/__init__.py
wrfrun/cli.py
wrfrun/data.py
wrfrun/run.py
wrfrun/utils.py
wrfrun/core/__init__.py
wrfrun/core/base.py
wrfrun/core/config.py
wrfrun/core/error.py
wrfrun/core/replay.py
wrfrun/core/server.py
wrfrun/extension/__init__.py
wrfrun/extension/utils.py
wrfrun/extension/goos_sst/__init__.py
wrfrun/extension/goos_sst/core.py
wrfrun/extension/goos_sst/utils.py
wrfrun/extension/goos_sst/res/__init__.py
wrfrun/extension/goos_sst/res/Vtable.ERA_GOOS_SST
wrfrun/extension/littler/__init__.py
wrfrun/extension/littler/core.py
wrfrun/model/__init__.py
wrfrun/model/base.py
wrfrun/model/plot.py
wrfrun/model/utils.py
wrfrun/model/wrf/__init__.py
wrfrun/model/wrf/core.py
wrfrun/model/wrf/exec_wrap.py
wrfrun/model/wrf/geodata.py
wrfrun/model/wrf/namelist.py
wrfrun/model/wrf/scheme.py
wrfrun/model/wrf/utils.py
wrfrun/model/wrf/vtable.py
wrfrun/plot/__init__.py
wrfrun/plot/wps.py
wrfrun/res/__init__.py
wrfrun/res/run.template.sh
wrfrun/res/config/config.template.toml
wrfrun/res/config/wrf.template.toml
wrfrun/res/extension/plotgrids.ncl
wrfrun/res/namelist/namelist.input.da_wrfvar.template
wrfrun/res/namelist/namelist.input.dfi.template
wrfrun/res/namelist/namelist.input.real.template
wrfrun/res/namelist/namelist.input.wrf.template
wrfrun/res/namelist/namelist.wps.template
wrfrun/res/namelist/parame.in.template
wrfrun/res/scheduler/lsf.template
wrfrun/res/scheduler/pbs.template
wrfrun/res/scheduler/slurm.template
wrfrun/scheduler/__init__.py
wrfrun/scheduler/env.py
wrfrun/scheduler/lsf.py
wrfrun/scheduler/pbs.py
wrfrun/scheduler/script.py
wrfrun/scheduler/slurm.py
wrfrun/scheduler/utils.py
wrfrun/workspace/__init__.py
wrfrun/workspace/core.py
wrfrun/workspace/wrf.py
wrfrun-0.1.9.dist-info/RECORD
