Metadata-Version: 2.1
Name: wrfrun
Version: 0.1.9
Summary: wrfrun is a comprehensive toolkit for managing and using WRF
Keywords: WRF
Author-Email: Syize <syizeliu@gmail.com>
Maintainer-Email: Syize <syizeliu@gmail.com>
License: GPL-3.0-or-later
Project-URL: homepage, https://github.com/Syize/wrfrun
Project-URL: repository, https://github.com/Syize/wrfrun
Project-URL: documentation, https://wrfrun.syize.cn
Project-URL: Bug Tracker, https://github.com/Syize/wrfrun/issues
Requires-Python: >=3.10
Requires-Dist: numpy
Requires-Dist: xarray
Requires-Dist: netCDF4
Requires-Dist: rich
Requires-Dist: pandas
Requires-Dist: f90nml
Requires-Dist: cdsapi
Requires-Dist: matplotlib
Requires-Dist: Cartopy
Requires-Dist: wrf-python
Requires-Dist: cfgrib
Requires-Dist: tomli
Requires-Dist: tomli-w
Requires-Dist: haversine
